LICENSE
README.md
setup.py
synkler/__init__.py
synkler.egg-info/PKG-INFO
synkler.egg-info/SOURCES.txt
synkler.egg-info/dependency_links.txt
synkler.egg-info/entry_points.txt
synkler.egg-info/requires.txt
synkler.egg-info/top_level.txt