Metadata-Version: 2.1
Name: synkler
Version: 0.0.7
Summary: A three-body rsync solution.
Home-page: https://github.com/pgillan145/synkler
Author: Patrick Gillan
Author-email: pgillan@minorimpact.com
License: GPLv3
Platform: UNKNOWN
License-File: LICENSE
